zemax/__init__.py
zemax/analysis/__init__.py
zemax/analysis/analysis.py
zemax/analysis/analysisIDM.py
zemax/core/__init__.py
zemax/core/optical_studio.py
zemax/core/zemax_dlls.py
zemax/core/zemax_dotnet.py
zemax/core/zemax_exceptions.py
zemax/core/zemax_reg.py
zemax/core/zemax_standalone.py
zemax/core/zemax_zmx.py
zemax/plotter/__init__.py
zemax/plotter/cmaps.py
zemax/plotter/histogram.py
zemax/plotter/old.py
zemax/plotter/parameters.py
zemax/plotter/plotter_array.py
zemax/plotter/scalarField2D.py
zemax/plotter/scalarField2D_array.py
zemax/psf/__init__.py
zemax/psf/crop_result.py
zemax/psf/psf.py
zemax/psf/psf_parameters.py
zemax/psf/psf_settings.py
zemax/raytracer/__init__.py
zemax/raytracer/raytracer.py
zemax/tools/__init__.py
zemax/tools/quickfocus.py
zemax/wrappers/__init__.py
zemax/wrappers/base_selector.py
zemax/wrappers/zos_data_series.py
zemax/wrappers/zos_datagrid.py
zemax/wrappers/zos_error_codes.py
zemax/wrappers/zos_field.py
zemax/wrappers/zos_ias.py
zemax/wrappers/zos_message.py
zemax/wrappers/zos_metadata.py
zemax/wrappers/zos_result.py
zemax/wrappers/zos_scatter_points.py
zemax/wrappers/zos_surface.py
zemax/wrappers/zos_wavelength.py
zemax-0.2.0.dist-info/licenses/LICENSE
zemax-0.2.0.dist-info/METADATA
zemax-0.2.0.dist-info/WHEEL
zemax-0.2.0.dist-info/top_level.txt
zemax-0.2.0.dist-info/RECORD
